batspp/__init__.py
batspp/__version__.py
batspp/_ast_nodes.py
batspp/_exceptions.py
batspp/_interpreter.py
batspp/_ipynb_to_batspp.py
batspp/_lexer.py
batspp/_parser.py
batspp/_settings.py
batspp/_token.py
batspp/batspp_args.py
batspp/batspp_opts.py
batspp/batspp_test.py
batspp-2.2.0.data/scripts/batspp
batspp-2.2.0.dist-info/LICENSE.txt
batspp-2.2.0.dist-info/METADATA
batspp-2.2.0.dist-info/WHEEL
batspp-2.2.0.dist-info/top_level.txt
batspp-2.2.0.dist-info/RECORD
