Metadata-Version: 2.1
Name: batspp
Version: 2.2.0
Summary: Shell style tests using bats-core
Home-page: https://github.com/LimaBD/batspp
Author: Bruno Daniel Lima
Author-email: bdl1998@hotmail.com
License: GNU Lesser General Public License v3 (LGPLv3)
Project-URL: Bug Tracker, https://github.com/LimaBD/batspp/issues
Platform: UNKNOWN
Classifier: Programming Language :: Python :: 3
Classifier: License :: OSI Approved :: GNU Lesser General Public License v3 (LGPLv3)
Classifier: Operating System :: OS Independent
Requires-Python: >=3.8
Requires-Dist: mezcla (==1.3.0)
Requires-Dist: six (==1.12.0)
